magestore_abp/__init__.py
magestore_abp/auto.py
magestore_abp/data/raw_build_package.sh
magestore_abp/data/raw_install_prerequisite.sh
magestore_abp-1.1.4.dist-info/METADATA
magestore_abp-1.1.4.dist-info/WHEEL
magestore_abp-1.1.4.dist-info/top_level.txt
magestore_abp-1.1.4.dist-info/RECORD
