Metadata-Version: 2.1
Name: magestore-abp
Version: 1.1.4
Summary: Add package requires to setup
Home-page: https://magestore.com
Author: Mars
Author-email: mars@trueplus.vn
License: UNKNOWN
Platform: UNKNOWN
Classifier: Programming Language :: Python :: 3
Requires-Python: >=3
Requires-Dist: requests
